{
    "key": "group_5701f4da4a3e2",
    "title": "Personnage - C\u00f4t\u00e9",
    "fields": [],
    "location": [
        [
            {
                "param": "post_type",
                "operator": "==",
                "value": "character"
            }
        ]
    ],
    "menu_order": 0,
    "position": "side",
    "style": "seamless",
    "label_placement": "top",
    "instruction_placement": "label",
    "hide_on_screen": "",
    "active": 1,
    "description": "",
    "modified": 1459746026
}